Workbook

Sheet START HERE ✦
A1: ⬡ AI TRADING JOURNAL COACH · Basic Edition (₹499) · thetradingmindset26 · @thetradingmindset26
A3: Welcome to your AI Trading Journal Coach.
A4: This journal tracks your trades, your emotions, your mistakes, and your setups — and shows you exactly where your money is going and why.
A6: WHAT IS INSIDE THIS JOURNAL:
A7: ✦ TRADE_LOG — Log every trade — 13 columns with dropdowns. Quality score auto-calculates.
A8: ✦ DASHBOARD — 10 live KPIs: Win Rate, Profit Factor, Discipline %, Expectancy, Equity Curve. All automatic.
A9: ✦ SETUP_ANALYSIS — Every setup ranked by Expected Value. Find out which setups actually make you money.
A10: ✦ PSYCHOLOGY_LOG — Emotion frequency table and pie chart. Tracks your emotional patterns automatically.
A11: ✦ WEEKLY_REVIEW — Type your week-end date. 5 metrics auto-calculate. Add your weekly reflection notes.
A12: ✦ AI_PROMPT — Pre-written coaching prompt with your live metrics. Copy and paste into any free AI.
A14: HOW TO USE THIS JOURNAL — 3 STEPS ONLY:
A15: STEP 1 → Go to the TRADE_LOG sheet. Delete the sample rows (rows 4 to 13). Start logging your own trades.
... A38: © thetradingmindset26 2026 · Basic Edition (₹499) · @thetradingmindset26 · Personal use only · Redistribution prohibited.

Sheet TRADE_LOG
A1: ⬡ TRADE LOG · BASIC EDITION · thetradingmindset26 · Fill one row per trade
A2: ✦ TRADE QUALITY (col L) and DECISION SCORE (col M) are AUTO-CALCULATED from your data. Do NOT type in those columns. | Use dropdowns for all other columns.
A3: DATE | B3: INSTRUMENT | C3: DIRECTION | D3: SETUP TYPE | E3: MARKET COND. | F3: ENTRY | G3: EXIT | H3: PnL (pts) | I3: R:R | J3: RULE? | K3: EMOTION BEFORE | L3: TRADE QUALITY (AUTO) | M3: NOTES
A4: 2026-03-20 | B4: Bank Nifty | C4: Long | D4: Breakout | E4: Trending | F4: 47850 | G4: 48050 | H4: 200 | I4: 2 | J4: Yes | K4: Confident | L4: =IFERROR(MAX(1,MIN(10,5+IF(I4>=2,2,IF(I4>=1.5,1,IF(I4<1,-1,0)))+IF(J4="Yes",1,-1)+IF(OR(E4="Trending",E4="Volatile"),1,0))),"") | M4: Clean BO above resistance
A5: 2026-03-20 | B5: Nifty 50 | C5: Short | D5: Reversal | E5: Ranging | F5: 22400 | G5: 22250 | H5: 150 | I5: 1.5 | J5: Yes | K5: Disciplined | L5: =IFERROR(MAX(1,MIN(10,5+IF(I5>=2,2,IF(I5>=1.5,1,IF(I5<1,-1,0)))+IF(J5="Yes",1,-1)+IF(OR(E5="Trending",E5="Volatile"),1,0))),"") | M5: OB rejection at HOD
A6: 2026-03-21 | B6: Bank Nifty | C6: Short | D6: Liquidity Grab | E6: Volatile | F6: 48100 | G6: 48350 | H6: -250 | I6: 0.8 | J6: No | K6: Fearful | L6: =IFERROR(MAX(1,MIN(10,5+IF(I6>=2,2,IF(I6>=1.5,1,IF(I6<1,-1,0)))+IF(J6="Yes",1,-1)+IF(OR(E6="Trending",E6="Volatile"),1,0))),"") | M6: SL moved
A7: 2026-03-24 | B7: Nifty 50 | C7: Long | D7: VWAP Reversion | E7: Ranging | F7: 22180 | G7: 22310 | H7: 130 | I7: 1.8 | J7: Yes | K7: Calm | L7: =IFERROR(MAX(1,MIN(10,5+IF(I7>=2,2,IF(I7>=1.5,1,IF(I7<1,-1,0)))+IF(J7="Yes",1,-1)+IF(OR(E7="Trending",E7="Volatile"),1,0))),"") | M7: VWAP reclaim clean
A8: 2026-03-24 | B8: Bank Nifty | C8: Short | D8: Breakdown | E8: Trending | F8: 47700 | G8: 47450 | H8: 250 | I8: 2.5 | J8: Yes | K8: Confident | L8: =IFERROR(MAX(1,MIN(10,5+IF(I8>=2,2,IF(I8>=1.5,1,IF(I8<1,-1,0)))+IF(J8="Yes",1,-1)+IF(OR(E8="Trending",E8="Volatile"),1,0))),"") | M8: BD below support
L9: =IFERROR(MAX(1,MIN(10,5+IF(I9>=2,2,IF(I9>=1.5,1,IF(I9<1,-1,0)))+IF(J9="Yes",1,-1)+IF(OR(E9="Trending",E9="Volatile"),1,0))),"")
L10: =IFERROR(MAX(1,MIN(10,5+IF(I10>=2,2,IF(I10>=1.5,1,IF(I10<1,-1,0)))+IF(J10="Yes",1,-1)+IF(OR(E10="Trending",E10="Volatile"),1,0))),"")
L11: =IFERROR(MAX(1,MIN(10,5+IF(I11>=2,2,IF(I11>=1.5,1,IF(I11<1,-1,0)))+IF(J11="Yes",1,-1)+IF(OR(E11="Trending",E11="Volatile"),1,0))),"")
L12: =IFERROR(MAX(1,MIN(10,5+IF(I12>=2,2,IF(I12>=1.5,1,IF(I12<1,-1,0)))+IF(J12="Yes",1,-1)+IF(OR(E12="Trending",E12="Volatile"),1,0))),"")
L13: =IFERROR(MAX(1,MIN(10,5+IF(I13>=2,2,IF(I13>=1.5,1,IF(I13<1,-1,0)))+IF(J13="Yes",1,-1)+IF(OR(E13="Trending",E13="Volatile"),1,0))),"")
L14: =IFERROR(MAX(1,MIN(10,5+IF(I14>=2,2,IF(I14>=1.5,1,IF(I14<1,-1,0)))+IF(J14="Yes",1,-1)+IF(OR(E14="Trending",E14="Volatile"),1,0))),"")
L15: =IFERROR(MAX(1,MIN(10,5+IF(I15>=2,2,IF(I15>=1.5,1,IF(I15<1,-1,0)))+IF(J15="Yes",1,-1)+IF(OR(E15="Trending",E15="Volatile"),1,0))),"")
L16: =IFERROR(MAX(1,MIN(10,5+IF(I16>=2,2,IF(I16>=1.5,1,IF(I16<1,-1,0)))+IF(J16="Yes",1,-1)+IF(OR(E16="Trending",E16="Volatile"),1,0))),"")
L17: =IFERROR(MAX(1,MIN(10,5+IF(I17>=2,2,IF(I17>=1.5,1,IF(I17<1,-1,0)))+IF(J17="Yes",1,-1)+IF(OR(E17="Trending",E17="Volatile"),1,0))),"")
L18: =IFERROR(MAX(1,MIN(10,5+IF(I18>=2,2,IF(I18>=1.5,1,IF(I18<1,-1,0)))+IF(J18="Yes",1,-1)+IF(OR(E18="Trending",E18="Volatile"),1,0))),"")
L19: =IFERROR(MAX(1,MIN(10,5+IF(I19>=2,2,IF(I19>=1.5,1,IF(I19<1,-1,0)))+IF(J19="Yes",1,-1)+IF(OR(E19="Trending",E19="Volatile"),1,0))),"")
L20: =IFERROR(MAX(1,MIN(10,5+IF(I20>=2,2,IF(I20>=1.5,1,IF(I20<1,-1,0)))+IF(J20="Yes",1,-1)+IF(OR(E20="Trending",E20="Volatile"),1,0))),"")
... L302: =IFERROR(MAX(1,MIN(10,5+IF(I302>=2,2,IF(I302>=1.5,1,IF(I302<1,-1,0)))+IF(J302="Yes",1,-1)+IF(OR(E302="Trending",E302="Volatile"),1,0))),"")
A304: © thetradingmindset26 2026 · Basic Edition (₹499) · @thetradingmindset26 · Educational self-improvement tool only. Not investment advice. Unauthorised redistribution prohibited.

Sheet DASHBOARD
A1: ⬡ PERFORMANCE DASHBOARD · BASIC EDITION · All data AUTO from TRADE_LOG
A2: Everything below updates automatically when you add trades to TRADE_LOG. You never type anything here.
A3: TOTAL TRADES | B3: WIN RATE | C3: TOTAL PnL | D3: PROFIT FACTOR | E3: AVG R:R | F3: DISCIPLINE % | G3: AVG WIN | H3: AVG LOSS | I3: EXPECTANCY | J3: AVG QUALITY
A4: =COUNTA(TRADE_LOG!A4:A2000) | B4: =IFERROR(COUNTIF(TRADE_LOG!H4:H2000,">0")/COUNTA(TRADE_LOG!H4:H2000),0) | C4: =IFERROR(SUM(TRADE_LOG!H4:H2000),0) | D4: =IFERROR(SUMIF(TRADE_LOG!H4:H2000,">0")/ABS(SUMIF(TRADE_LOG!H4:H2000,"<0")),0) | E4: =IFERROR(AVERAGE(TRADE_LOG!I4:I2000),0) | F4: =IFERROR(COUNTIF(TRADE_LOG!J4:J2000,"Yes")/COUNTA(TRADE_LOG!J4:J2000),0) | G4: =IFERROR(AVERAGEIF(TRADE_LOG!H4:H2000,">0",TRADE_LOG!H4:H2000),0) | H4: =IFERROR(ABS(AVERAGEIF(TRADE_LOG!H4:H2000,"<0",TRADE_LOG!H4:H2000)),0) | I4: =IFERROR((COUNTIF(TRADE_LOG!H4:H2000,">0")/COUNTA(TRADE_LOG!H4:H2000))*AVERAGEIF(TRADE_LOG!H4:H2000,">0",TRADE_LOG!H4:H2000)+(COUNTIF(TRADE_LOG!H4:H2000,"<0")/COUNTA(TRADE_LOG!H4:H2000))*AVERAGEIF(TRADE_LOG!H4:H2000,"<0",TRADE_LOG!H4:H2000),0) | J4: =IFERROR(AVERAGE(TRADE_LOG!L4:L2000),0)
A5: EQUITY CURVE DATA (auto-calculated):
A6: Trade # | B6: Date | C6: PnL | D6: Cumulative PnL | E6: Rolling Win Rate
A7: =IF(TRADE_LOG!A4<>"",1,"") | B7: =IF(TRADE_LOG!A4<>"",TRADE_LOG!A4,"") | C7: =IF(TRADE_LOG!H4<>"",TRADE_LOG!H4,"") | D7: =IF(C7<>"",C7,"") | E7: =IFERROR(COUNTIF(TRADE_LOG!H$4:H$4,">0")/COUNTA(TRADE_LOG!H$4:H$4),"")
A8: =IF(TRADE_LOG!A5<>"",2,"") | B8: =IF(TRADE_LOG!A5<>"",TRADE_LOG!A5,"") | C8: =IF(TRADE_LOG!H5<>"",TRADE_LOG!H5,"") | D8: =IF(C8<>"",D7+C8,"") | E8: =IFERROR(COUNTIF(TRADE_LOG!H$4:H$5,">0")/COUNTA(TRADE_LOG!H$4:H$5),"")
A9: =IF(TRADE_LOG!A6<>"",3,"") | B9: =IF(TRADE_LOG!A6<>"",TRADE_LOG!A6,"") | C9: =IF(TRADE_LOG!H6<>"",TRADE_LOG!H6,"") | D9: =IF(C9<>"",D8+C9,"") | E9: =IFERROR(COUNTIF(TRADE_LOG!H$4:H$6,">0")/COUNTA(TRADE_LOG!H$4:H$6),"")
A10: =IF(TRADE_LOG!A7<>"",4,"") | B10: =IF(TRADE_LOG!A7<>"",TRADE_LOG!A7,"") | C10: =IF(TRADE_LOG!H7<>"",TRADE_LOG!H7,"") | D10: =IF(C10<>"",D9+C10,"") | E10: =IFERROR(COUNTIF(TRADE_LOG!H$4:H$7,">0")/COUNTA(TRADE_LOG!H$4:H$7),"")
A11: =IF(TRADE_LOG!A8<>"",5,"") | B11: =IF(TRADE_LOG!A8<>"",TRADE_LOG!A8,"") | C11: =IF(TRADE_LOG!H8<>"",TRADE_LOG!H8,"") | D11: =IF(C11<>"",D10+C11,"") | E11: =IFERROR(COUNTIF(TRADE_LOG!H$4:H$8,">0")/COUNTA(TRADE_LOG!H$4:H$8),"")
A12: =IF(TRADE_LOG!A9<>"",6,"") | B12: =IF(TRADE_LOG!A9<>"",TRADE_LOG!A9,"") | C12: =IF(TRADE_LOG!H9<>"",TRADE_LOG!H9,"") | D12: =IF(C12<>"",D11+C12,"") | E12: =IFERROR(COUNTIF(TRADE_LOG!H$4:H$9,">0")/COUNTA(TRADE_LOG!H$4:H$9),"")
A13: =IF(TRADE_LOG!A10<>"",7,"") | B13: =IF(TRADE_LOG!A10<>"",TRADE_LOG!A10,"") | C13: =IF(TRADE_LOG!H10<>"",TRADE_LOG!H10,"") | D13: =IF(C13<>"",D12+C13,"") | E13: =IFERROR(COUNTIF(TRADE_LOG!H$4:H$10,">0")/COUNTA(TRADE_LOG!H$4:H$10),"")
A14: =IF(TRADE_LOG!A11<>"",8,"") | B14: =IF(TRADE_LOG!A11<>"",TRADE_LOG!A11,"") | C14: =IF(TRADE_LOG!H11<>"",TRADE_LOG!H11,"") | D14: =IF(C14<>"",D13+C14,"") | E14: =IFERROR(COUNTIF(TRADE_LOG!H$4:H$11,">0")/COUNTA(TRADE_LOG!H$4:H$11),"")
A15: =IF(TRADE_LOG!A12<>"",9,"") | B15: =IF(TRADE_LOG!A12<>"",TRADE_LOG!A12,"") | C15: =IF(TRADE_LOG!H12<>"",TRADE_LOG!H12,"") | D15: =IF(C15<>"",D14+C15,"") | E15: =IFERROR(COUNTIF(TRADE_LOG!H$4:H$12,">0")/COUNTA(TRADE_LOG!H$4:H$12),"")
A16: =IF(TRADE_LOG!A13<>"",10,"") | B16: =IF(TRADE_LOG!A13<>"",TRADE_LOG!A13,"") | C16: =IF(TRADE_LOG!H13<>"",TRADE_LOG!H13,"") | D16: =IF(C16<>"",D15+C16,"") | E16: =IFERROR(COUNTIF(TRADE_LOG!H$4:H$13,">0")/COUNTA(TRADE_LOG!H$4:H$13),"")
A17: =IF(TRADE_LOG!A14<>"",11,"") | B17: =IF(TRADE_LOG!A14<>"",TRADE_LOG!A14,"") | C17: =IF(TRADE_LOG!H14<>"",TRADE_LOG!H14,"") | D17: =IF(C17<>"",D16+C17,"") | E17: =IFERROR(COUNTIF(TRADE_LOG!H$4:H$14,">0")/COUNTA(TRADE_LOG!H$4:H$14),"")
A18: =IF(TRADE_LOG!A15<>"",12,"") | B18: =IF(TRADE_LOG!A15<>"",TRADE_LOG!A15,"") | C18: =IF(TRADE_LOG!H15<>"",TRADE_LOG!H15,"") | D18: =IF(C18<>"",D17+C18,"") | E18: =IFERROR(COUNTIF(TRADE_LOG!H$4:H$15,">0")/COUNTA(TRADE_LOG!H$4:H$15),"")
A19: =IF(TRADE_LOG!A16<>"",13,"") | B19: =IF(TRADE_LOG!A16<>"",TRADE_LOG!A16,"") | C19: =IF(TRADE_LOG!H16<>"",TRADE_LOG!H16,"") | D19: =IF(C19<>"",D18+C19,"") | E19: =IFERROR(COUNTIF(TRADE_LOG!H$4:H$16,">0")/COUNTA(TRADE_LOG!H$4:H$16),"")
A20: =IF(TRADE_LOG!A17<>"",14,"") | B20: =IF(TRADE_LOG!A17<>"",TRADE_LOG!A17,"") | C20: =IF(TRADE_LOG!H17<>"",TRADE_LOG!H17,"") | D20: =IF(C20<>"",D19+C20,"") | E20: =IFERROR(COUNTIF(TRADE_LOG!H$4:H$17,">0")/COUNTA(TRADE_LOG!H$4:H$17),"")
A21: =IF(TRADE_LOG!A18<>"",15,"") | B21: =IF(TRADE_LOG!A18<>"",TRADE_LOG!A18,"") | C21: =IF(TRADE_LOG!H18<>"",TRADE_LOG!H18,"") | D21: =IF(C21<>"",D20+C21,"") | E21: =IFERROR(COUNTIF(TRADE_LOG!H$4:H$18,">0")/COUNTA(TRADE_LOG!H$4:H$18),"")
A22: =IF(TRADE_LOG!A19<>"",16,"") | B22: =IF(TRADE_LOG!A19<>"",TRADE_LOG!A19,"") | C22: =IF(TRADE_LOG!H19<>"",TRADE_LOG!H19,"") | D22: =IF(C22<>"",D21+C22,"") | E22: =IFERROR(COUNTIF(TRADE_LOG!H$4:H$19,">0")/COUNTA(TRADE_LOG!H$4:H$19),"")
A23: =IF(TRADE_LOG!A20<>"",17,"") | B23: =IF(TRADE_LOG!A20<>"",TRADE_LOG!A20,"") | C23: =IF(TRADE_LOG!H20<>"",TRADE_LOG!H20,"") | D23: =IF(C23<>"",D22+C23,"") | E23: =IFERROR(COUNTIF(TRADE_LOG!H$4:H$20,">0")/COUNTA(TRADE_LOG!H$4:H$20),"")
A24: =IF(TRADE_LOG!A21<>"",18,"") | B24: =IF(TRADE_LOG!A21<>"",TRADE_LOG!A21,"") | C24: =IF(TRADE_LOG!H21<>"",TRADE_LOG!H21,"") | D24: =IF(C24<>"",D23+C24,"") | E24: =IFERROR(COUNTIF(TRADE_LOG!H$4:H$21,">0")/COUNTA(TRADE_LOG!H$4:H$21),"")
A25: =IF(TRADE_LOG!A22<>"",19,"") | B25: =IF(TRADE_LOG!A22<>"",TRADE_LOG!A22,"") | C25: =IF(TRADE_LOG!H22<>"",TRADE_LOG!H22,"") | D25: =IF(C25<>"",D24+C25,"") | E25: =IFERROR(COUNTIF(TRADE_LOG!H$4:H$22,">0")/COUNTA(TRADE_LOG!H$4:H$22),"")
A26: =IF(TRADE_LOG!A23<>"",20,"") | B26: =IF(TRADE_LOG!A23<>"",TRADE_LOG!A23,"") | C26: =IF(TRADE_LOG!H23<>"",TRADE_LOG!H23,"") | D26: =IF(C26<>"",D25+C26,"") | E26: =IFERROR(COUNTIF(TRADE_LOG!H$4:H$23,">0")/COUNTA(TRADE_LOG!H$4:H$23),"")
A27: =IF(TRADE_LOG!A24<>"",21,"") | B27: =IF(TRADE_LOG!A24<>"",TRADE_LOG!A24,"") | C27: =IF(TRADE_LOG!H24<>"",TRADE_LOG!H24,"") | D27: =IF(C27<>"",D26+C27,"") | E27: =IFERROR(COUNTIF(TRADE_LOG!H$4:H$24,">0")/COUNTA(TRADE_LOG!H$4:H$24),"")
A28: =IF(TRADE_LOG!A25<>"",22,"") | B28: =IF(TRADE_LOG!A25<>"",TRADE_LOG!A25,"") | C28: =IF(TRADE_LOG!H25<>"",TRADE_LOG!H25,"") | D28: =IF(C28<>"",D27+C28,"") | E28: =IFERROR(COUNTIF(TRADE_LOG!H$4:H$25,">0")/COUNTA(TRADE_LOG!H$4:H$25),"")
A29: =IF(TRADE_LOG!A26<>"",23,"") | B29: =IF(TRADE_LOG!A26<>"",TRADE_LOG!A26,"") | C29: =IF(TRADE_LOG!H26<>"",TRADE_LOG!H26,"") | D29: =IF(C29<>"",D28+C29,"") | E29: =IFERROR(COUNTIF(TRADE_LOG!H$4:H$26,">0")/COUNTA(TRADE_LOG!H$4:H$26),"")
A30: =IF(TRADE_LOG!A27<>"",24,"") | B30: =IF(TRADE_LOG!A27<>"",TRADE_LOG!A27,"") | C30: =IF(TRADE_LOG!H27<>"",TRADE_LOG!H27,"") | D30: =IF(C30<>"",D29+C30,"") | E30: =IFERROR(COUNTIF(TRADE_LOG!H$4:H$27,">0")/COUNTA(TRADE_LOG!H$4:H$27),"")
A31: =IF(TRADE_LOG!A28<>"",25,"") | B31: =IF(TRADE_LOG!A28<>"",TRADE_LOG!A28,"") | C31: =IF(TRADE_LOG!H28<>"",TRADE_LOG!H28,"") | D31: =IF(C31<>"",D30+C31,"") | E31: =IFERROR(COUNTIF(TRADE_LOG!H$4:H$28,">0")/COUNTA(TRADE_LOG!H$4:H$28),"")
A32: =IF(TRADE_LOG!A29<>"",26,"") | B32: =IF(TRADE_LOG!A29<>"",TRADE_LOG!A29,"") | C32: =IF(TRADE_LOG!H29<>"",TRADE_LOG!H29,"") | D32: =IF(C32<>"",D31+C32,"") | E32: =IFERROR(COUNTIF(TRADE_LOG!H$4:H$29,">0")/COUNTA(TRADE_LOG!H$4:H$29),"")
A33: =IF(TRADE_LOG!A30<>"",27,"") | B33: =IF(TRADE_LOG!A30<>"",TRADE_LOG!A30,"") | C33: =IF(TRADE_LOG!H30<>"",TRADE_LOG!H30,"") | D33: =IF(C33<>"",D32+C33,"") | E33: =IFERROR(COUNTIF(TRADE_LOG!H$4:H$30,">0")/COUNTA(TRADE_LOG!H$4:H$30),"")
A34: =IF(TRADE_LOG!A31<>"",28,"") | B34: =IF(TRADE_LOG!A31<>"",TRADE_LOG!A31,"") | C34: =IF(TRADE_LOG!H31<>"",TRADE_LOG!H31,"") | D34: =IF(C34<>"",D33+C34,"") | E34: =IFERROR(COUNTIF(TRADE_LOG!H$4:H$31,">0")/COUNTA(TRADE_LOG!H$4:H$31),"")
A35: =IF(TRADE_LOG!A32<>"",29,"") | B35: =IF(TRADE_LOG!A32<>"",TRADE_LOG!A32,"") | C35: =IF(TRADE_LOG!H32<>"",TRADE_LOG!H32,"") | D35: =IF(C35<>"",D34+C35,"") | E35: =IFERROR(COUNTIF(TRADE_LOG!H$4:H$32,">0")/COUNTA(TRADE_LOG!H$4:H$32),"")
A36: =IF(TRADE_LOG!A33<>"",30,"") | B36: =IF(TRADE_LOG!A33<>"",TRADE_LOG!A33,"") | C36: =IF(TRADE_LOG!H33<>"",TRADE_LOG!H33,"") | D36: =IF(C36<>"",D35+C36,"") | E36: =IFERROR(COUNTIF(TRADE_LOG!H$4:H$33,">0")/COUNTA(TRADE_LOG!H$4:H$33),"")
A37: =IF(TRADE_LOG!A34<>"",31,"") | B37: =IF(TRADE_LOG!A34<>"",TRADE_LOG!A34,"") | C37: =IF(TRADE_LOG!H34<>"",TRADE_LOG!H34,"") | D37: =IF(C37<>"",D36+C37,"") | E37: =IFERROR(COUNTIF(TRADE_LOG!H$4:H$34,">0")/COUNTA(TRADE_LOG!H$4:H$34),"")
A38: =IF(TRADE_LOG!A35<>"",32,"") | B38: =IF(TRADE_LOG!A35<>"",TRADE_LOG!A35,"") | C38: =IF(TRADE_LOG!H35<>"",TRADE_LOG!H35,"") | D38: =IF(C38<>"",D37+C38,"") | E38: =IFERROR(COUNTIF(TRADE_LOG!H$4:H$35,">0")/COUNTA(TRADE_LOG!H$4:H$35),"")
A39: =IF(TRADE_LOG!A36<>"",33,"") | B39: =IF(TRADE_LOG!A36<>"",TRADE_LOG!A36,"") | C39: =IF(TRADE_LOG!H36<>"",TRADE_LOG!H36,"") | D39: =IF(C39<>"",D38+C39,"") | E39: =IFERROR(COUNTIF(TRADE_LOG!H$4:H$36,">0")/COUNTA(TRADE_LOG!H$4:H$36),"")
A40: =IF(TRADE_LOG!A37<>"",34,"") | B40: =IF(TRADE_LOG!A37<>"",TRADE_LOG!A37,"") | C40: =IF(TRADE_LOG!H37<>"",TRADE_LOG!H37,"") | D40: =IF(C40<>"",D39+C40,"") | E40: =IFERROR(COUNTIF(TRADE_LOG!H$4:H$37,">0")/COUNTA(TRADE_LOG!H$4:H$37),"")
A41: =IF(TRADE_LOG!A38<>"",35,"") | B41: =IF(TRADE_LOG!A38<>"",TRADE_LOG!A38,"") | C41: =IF(TRADE_LOG!H38<>"",TRADE_LOG!H38,"") | D41: =IF(C41<>"",D40+C41,"") | E41: =IFERROR(COUNTIF(TRADE_LOG!H$4:H$38,">0")/COUNTA(TRADE_LOG!H$4:H$38),"")
A42: =IF(TRADE_LOG!A39<>"",36,"") | B42: =IF(TRADE_LOG!A39<>"",TRADE_LOG!A39,"") | C42: =IF(TRADE_LOG!H39<>"",TRADE_LOG!H39,"") | D42: =IF(C42<>"",D41+C42,"") | E42: =IFERROR(COUNTIF(TRADE_LOG!H$4:H$39,">0")/COUNTA(TRADE_LOG!H$4:H$39),"")
A43: =IF(TRADE_LOG!A40<>"",37,"") | B43: =IF(TRADE_LOG!A40<>"",TRADE_LOG!A40,"") | C43: =IF(TRADE_LOG!H40<>"",TRADE_LOG!H40,"") | D43: =IF(C43<>"",D42+C43,"") | E43: =IFERROR(COUNTIF(TRADE_LOG!H$4:H$40,">0")/COUNTA(TRADE_LOG!H$4:H$40),"")
A44: =IF(TRADE_LOG!A41<>"",38,"") | B44: =IF(TRADE_LOG!A41<>"",TRADE_LOG!A41,"") | C44: =IF(TRADE_LOG!H41<>"",TRADE_LOG!H41,"") | D44: =IF(C44<>"",D43+C44,"") | E44: =IFERROR(COUNTIF(TRADE_LOG!H$4:H$41,">0")/COUNTA(TRADE_LOG!H$4:H$41),"")
A45: =IF(TRADE_LOG!A42<>"",39,"") | B45: =IF(TRADE_LOG!A42<>"",TRADE_LOG!A42,"") | C45: =IF(TRADE_LOG!H42<>"",TRADE_LOG!H42,"") | D45: =IF(C45<>"",D44+C45,"") | E45: =IFERROR(COUNTIF(TRADE_LOG!H$4:H$42,">0")/COUNTA(TRADE_LOG!H$4:H$42),"")
A46: =IF(TRADE_LOG!A43<>"",40,"") | B46: =IF(TRADE_LOG!A43<>"",TRADE_LOG!A43,"") | C46: =IF(TRADE_LOG!H43<>"",TRADE_LOG!H43,"") | D46: =IF(C46<>"",D45+C46,"") | E46: =IFERROR(COUNTIF(TRADE_LOG!H$4:H$43,">0")/COUNTA(TRADE_LOG!H$4:H$43),"")
A47: =IF(TRADE_LOG!A44<>"",41,"") | B47: =IF(TRADE_LOG!A44<>"",TRADE_LOG!A44,"") | C47: =IF(TRADE_LOG!H44<>"",TRADE_LOG!H44,"") | D47: =IF(C47<>"",D46+C47,"") | E47: =IFERROR(COUNTIF(TRADE_LOG!H$4:H$44,">0")/COUNTA(TRADE_LOG!H$4:H$44),"")
A48: =IF(TRADE_LOG!A45<>"",42,"") | B48: =IF(TRADE_LOG!A45<>"",TRADE_LOG!A45,"") | C48: =IF(TRADE_LOG!H45<>"",TRADE_LOG!H45,"") | D48: =IF(C48<>"",D47+C48,"") | E48: =IFERROR(COUNTIF(TRADE_LOG!H$4:H$45,">0")/COUNTA(TRADE_LOG!H$4:H$45),"")
A49: =IF(TRADE_LOG!A46<>"",43,"") | B49: =IF(TRADE_LOG!A46<>"",TRADE_LOG!A46,"") | C49: =IF(TRADE_LOG!H46<>"",TRADE_LOG!H46,"") | D49: =IF(C49<>"",D48+C49,"") | E49: =IFERROR(COUNTIF(TRADE_LOG!H$4:H$46,">0")/COUNTA(TRADE_LOG!H$4:H$46),"")
A50: =IF(TRADE_LOG!A47<>"",44,"") | B50: =IF(TRADE_LOG!A47<>"",TRADE_LOG!A47,"") | C50: =IF(TRADE_LOG!H47<>"",TRADE_LOG!H47,"") | D50: =IF(C50<>"",D49+C50,"") | E50: =IFERROR(COUNTIF(TRADE_LOG!H$4:H$47,">0")/COUNTA(TRADE_LOG!H$4:H$47),"")
A51: =IF(TRADE_LOG!A48<>"",45,"") | B51: =IF(TRADE_LOG!A48<>"",TRADE_LOG!A48,"") | C51: =IF(TRADE_LOG!H48<>"",TRADE_LOG!H48,"") | D51: =IF(C51<>"",D50+C51,"") | E51: =IFERROR(COUNTIF(TRADE_LOG!H$4:H$48,">0")/COUNTA(TRADE_LOG!H$4:H$48),"")
A52: =IF(TRADE_LOG!A49<>"",46,"") | B52: =IF(TRADE_LOG!A49<>"",TRADE_LOG!A49,"") | C52: =IF(TRADE_LOG!H49<>"",TRADE_LOG!H49,"") | D52: =IF(C52<>"",D51+C52,"") | E52: =IFERROR(COUNTIF(TRADE_LOG!H$4:H$49,">0")/COUNTA(TRADE_LOG!H$4:H$49),"")
A53: =IF(TRADE_LOG!A50<>"",47,"") | B53: =IF(TRADE_LOG!A50<>"",TRADE_LOG!A50,"") | C53: =IF(TRADE_LOG!H50<>"",TRADE_LOG!H50,"") | D53: =IF(C53<>"",D52+C53,"") | E53: =IFERROR(COUNTIF(TRADE_LOG!H$4:H$50,">0")/COUNTA(TRADE_LOG!H$4:H$50),"")
A54: =IF(TRADE_LOG!A51<>"",48,"") | B54: =IF(TRADE_LOG!A51<>"",TRADE_LOG!A51,"") | C54: =IF(TRADE_LOG!H51<>"",TRADE_LOG!H51,"") | D54: =IF(C54<>"",D53+C54,"") | E54: =IFERROR(COUNTIF(TRADE_LOG!H$4:H$51,">0")/COUNTA(TRADE_LOG!H$4:H$51),"")
A55: =IF(TRADE_LOG!A52<>"",49,"") | B55: =IF(TRADE_LOG!A52<>"",TRADE_LOG!A52,"") | C55: =IF(TRADE_LOG!H52<>"",TRADE_LOG!H52,"") | D55: =IF(C55<>"",D54+C55,"") | E55: =IFERROR(COUNTIF(TRADE_LOG!H$4:H$52,">0")/COUNTA(TRADE_LOG!H$4:H$52),"")
A56: =IF(TRADE_LOG!A53<>"",50,"") | B56: =IF(TRADE_LOG!A53<>"",TRADE_LOG!A53,"") | C56: =IF(TRADE_LOG!H53<>"",TRADE_LOG!H53,"") | D56: =IF(C56<>"",D55+C56,"") | E56: =IFERROR(COUNTIF(TRADE_LOG!H$4:H$53,">0")/COUNTA(TRADE_LOG!H$4:H$53),"")
A57: =IF(TRADE_LOG!A54<>"",51,"") | B57: =IF(TRADE_LOG!A54<>"",TRADE_LOG!A54,"") | C57: =IF(TRADE_LOG!H54<>"",TRADE_LOG!H54,"") | D57: =IF(C57<>"",D56+C57,"") | E57: =IFERROR(COUNTIF(TRADE_LOG!H$4:H$54,">0")/COUNTA(TRADE_LOG!H$4:H$54),"")
A58: =IF(TRADE_LOG!A55<>"",52,"") | B58: =IF(TRADE_LOG!A55<>"",TRADE_LOG!A55,"") | C58: =IF(TRADE_LOG!H55<>"",TRADE_LOG!H55,"") | D58: =IF(C58<>"",D57+C58,"") | E58: =IFERROR(COUNTIF(TRADE_LOG!H$4:H$55,">0")/COUNTA(TRADE_LOG!H$4:H$55),"")
A59: =IF(TRADE_LOG!A56<>"",53,"") | B59: =IF(TRADE_LOG!A56<>"",TRADE_LOG!A56,"") | C59: =IF(TRADE_LOG!H56<>"",TRADE_LOG!H56,"") | D59: =IF(C59<>"",D58+C59,"") | E59: =IFERROR(COUNTIF(TRADE_LOG!H$4:H$56,">0")/COUNTA(TRADE_LOG!H$4:H$56),"")
A60: =IF(TRADE_LOG!A57<>"",54,"") | B60: =IF(TRADE_LOG!A57<>"",TRADE_LOG!A57,"") | C60: =IF(TRADE_LOG!H57<>"",TRADE_LOG!H57,"") | D60: =IF(C60<>"",D59+C60,"") | E60: =IFERROR(COUNTIF(TRADE_LOG!H$4:H$57,">0")/COUNTA(TRADE_LOG!H$4:H$57),"")
A61: =IF(TRADE_LOG!A58<>"",55,"") | B61: =IF(TRADE_LOG!A58<>"",TRADE_LOG!A58,"") | C61: =IF(TRADE_LOG!H58<>"",TRADE_LOG!H58,"") | D61: =IF(C61<>"",D60+C61,"") | E61: =IFERROR(COUNTIF(TRADE_LOG!H$4:H$58,">0")/COUNTA(TRADE_LOG!H$4:H$58),"")
A62: =IF(TRADE_LOG!A59<>"",56,"") | B62: =IF(TRADE_LOG!A59<>"",TRADE_LOG!A59,"") | C62: =IF(TRADE_LOG!H59<>"",TRADE_LOG!H59,"") | D62: =IF(C62<>"",D61+C62,"") | E62: =IFERROR(COUNTIF(TRADE_LOG!H$4:H$59,">0")/COUNTA(TRADE_LOG!H$4:H$59),"")
A63: =IF(TRADE_LOG!A60<>"",57,"") | B63: =IF(TRADE_LOG!A60<>"",TRADE_LOG!A60,"") | C63: =IF(TRADE_LOG!H60<>"",TRADE_LOG!H60,"") | D63: =IF(C63<>"",D62+C63,"") | E63: =IFERROR(COUNTIF(TRADE_LOG!H$4:H$60,">0")/COUNTA(TRADE_LOG!H$4:H$60),"")
A64: =IF(TRADE_LOG!A61<>"",58,"") | B64: =IF(TRADE_LOG!A61<>"",TRADE_LOG!A61,"") | C64: =IF(TRADE_LOG!H61<>"",TRADE_LOG!H61,"") | D64: =IF(C64<>"",D63+C64,"") | E64: =IFERROR(COUNTIF(TRADE_LOG!H$4:H$61,">0")/COUNTA(TRADE_LOG!H$4:H$61),"")
A65: =IF(TRADE_LOG!A62<>"",59,"") | B65: =IF(TRADE_LOG!A62<>"",TRADE_LOG!A62,"") | C65: =IF(TRADE_LOG!H62<>"",TRADE_LOG!H62,"") | D65: =IF(C65<>"",D64+C65,"") | E65: =IFERROR(COUNTIF(TRADE_LOG!H$4:H$62,">0")/COUNTA(TRADE_LOG!H$4:H$62),"")
A66: =IF(TRADE_LOG!A63<>"",60,"") | B66: =IF(TRADE_LOG!A63<>"",TRADE_LOG!A63,"") | C66: =IF(TRADE_LOG!H63<>"",TRADE_LOG!H63,"") | D66: =IF(C66<>"",D65+C66,"") | E66: =IFERROR(COUNTIF(TRADE_LOG!H$4:H$63,">0")/COUNTA(TRADE_LOG!H$4:H$63),"")
A67: =IF(TRADE_LOG!A64<>"",61,"") | B67: =IF(TRADE_LOG!A64<>"",TRADE_LOG!A64,"") | C67: =IF(TRADE_LOG!H64<>"",TRADE_LOG!H64,"") | D67: =IF(C67<>"",D66+C67,"") | E67: =IFERROR(COUNTIF(TRADE_LOG!H$4:H$64,">0")/COUNTA(TRADE_LOG!H$4:H$64),"")
A68: =IF(TRADE_LOG!A65<>"",62,"") | B68: =IF(TRADE_LOG!A65<>"",TRADE_LOG!A65,"") | C68: =IF(TRADE_LOG!H65<>"",TRADE_LOG!H65,"") | D68: =IF(C68<>"",D67+C68,"") | E68: =IFERROR(COUNTIF(TRADE_LOG!H$4:H$65,">0")/COUNTA(TRADE_LOG!H$4:H$65),"")
A69: =IF(TRADE_LOG!A66<>"",63,"") | B69: =IF(TRADE_LOG!A66<>"",TRADE_LOG!A66,"") | C69: =IF(TRADE_LOG!H66<>"",TRADE_LOG!H66,"") | D69: =IF(C69<>"",D68+C69,"") | E69: =IFERROR(COUNTIF(TRADE_LOG!H$4:H$66,">0")/COUNTA(TRADE_LOG!H$4:H$66),"")
A70: =IF(TRADE_LOG!A67<>"",64,"") | B70: =IF(TRADE_LOG!A67<>"",TRADE_LOG!A67,"") | C70: =IF(TRADE_LOG!H67<>"",TRADE_LOG!H67,"") | D70: =IF(C70<>"",D69+C70,"") | E70: =IFERROR(COUNTIF(TRADE_LOG!H$4:H$67,">0")/COUNTA(TRADE_LOG!H$4:H$67),"")
A71: =IF(TRADE_LOG!A68<>"",65,"") | B71: =IF(TRADE_LOG!A68<>"",TRADE_LOG!A68,"") | C71: =IF(TRADE_LOG!H68<>"",TRADE_LOG!H68,"") | D71: =IF(C71<>"",D70+C71,"") | E71: =IFERROR(COUNTIF(TRADE_LOG!H$4:H$68,">0")/COUNTA(TRADE_LOG!H$4:H$68),"")
A72: =IF(TRADE_LOG!A69<>"",66,"") | B72: =IF(TRADE_LOG!A69<>"",TRADE_LOG!A69,"") | C72: =IF(TRADE_LOG!H69<>"",TRADE_LOG!H69,"") | D72: =IF(C72<>"",D71+C72,"") | E72: =IFERROR(COUNTIF(TRADE_LOG!H$4:H$69,">0")/COUNTA(TRADE_LOG!H$4:H$69),"")
A73: =IF(TRADE_LOG!A70<>"",67,"") | B73: =IF(TRADE_LOG!A70<>"",TRADE_LOG!A70,"") | C73: =IF(TRADE_LOG!H70<>"",TRADE_LOG!H70,"") | D73: =IF(C73<>"",D72+C73,"") | E73: =IFERROR(COUNTIF(TRADE_LOG!H$4:H$70,">0")/COUNTA(TRADE_LOG!H$4:H$70),"")
A74: =IF(TRADE_LOG!A71<>"",68,"") | B74: =IF(TRADE_LOG!A71<>"",TRADE_LOG!A71,"") | C74: =IF(TRADE_LOG!H71<>"",TRADE_LOG!H71,"") | D74: =IF(C74<>"",D73+C74,"") | E74: =IFERROR(COUNTIF(TRADE_LOG!H$4:H$71,">0")/COUNTA(TRADE_LOG!H$4:H$71),"")
A75: =IF(TRADE_LOG!A72<>"",69,"") | B75: =IF(TRADE_LOG!A72<>"",TRADE_LOG!A72,"") | C75: =IF(TRADE_LOG!H72<>"",TRADE_LOG!H72,"") | D75: =IF(C75<>"",D74+C75,"") | E75: =IFERROR(COUNTIF(TRADE_LOG!H$4:H$72,">0")/COUNTA(TRADE_LOG!H$4:H$72),"")
A76: =IF(TRADE_LOG!A73<>"",70,"") | B76: =IF(TRADE_LOG!A73<>"",TRADE_LOG!A73,"") | C76: =IF(TRADE_LOG!H73<>"",TRADE_LOG!H73,"") | D76: =IF(C76<>"",D75+C76,"") | E76: =IFERROR(COUNTIF(TRADE_LOG!H$4:H$73,">0")/COUNTA(TRADE_LOG!H$4:H$73),"")
A77: =IF(TRADE_LOG!A74<>"",71,"") | B77: =IF(TRADE_LOG!A74<>"",TRADE_LOG!A74,"") | C77: =IF(TRADE_LOG!H74<>"",TRADE_LOG!H74,"") | D77: =IF(C77<>"",D76+C77,"") | E77: =IFERROR(COUNTIF(TRADE_LOG!H$4:H$74,">0")/COUNTA(TRADE_LOG!H$4:H$74),"")
A78: =IF(TRADE_LOG!A75<>"",72,"") | B78: =IF(TRADE_LOG!A75<>"",TRADE_LOG!A75,"") | C78: =IF(TRADE_LOG!H75<>"",TRADE_LOG!H75,"") | D78: =IF(C78<>"",D77+C78,"") | E78: =IFERROR(COUNTIF(TRADE_LOG!H$4:H$75,">0")/COUNTA(TRADE_LOG!H$4:H$75),"")
A79: =IF(TRADE_LOG!A76<>"",73,"") | B79: =IF(TRADE_LOG!A76<>"",TRADE_LOG!A76,"") | C79: =IF(TRADE_LOG!H76<>"",TRADE_LOG!H76,"") | D79: =IF(C79<>"",D78+C79,"") | E79: =IFERROR(COUNTIF(TRADE_LOG!H$4:H$76,">0")/COUNTA(TRADE_LOG!H$4:H$76),"")
A80: =IF(TRADE_LOG!A77<>"",74,"") | B80: =IF(TRADE_LOG!A77<>"",TRADE_LOG!A77,"") | C80: =IF(TRADE_LOG!H77<>"",TRADE_LOG!H77,"") | D80: =IF(C80<>"",D79+C80,"") | E80: =IFERROR(COUNTIF(TRADE_LOG!H$4:H$77,">0")/COUNTA(TRADE_LOG!H$4:H$77),"")
A81: =IF(TRADE_LOG!A78<>"",75,"") | B81: =IF(TRADE_LOG!A78<>"",TRADE_LOG!A78,"") | C81: =IF(TRADE_LOG!H78<>"",TRADE_LOG!H78,"") | D81: =IF(C81<>"",D80+C81,"") | E81: =IFERROR(COUNTIF(TRADE_LOG!H$4:H$78,">0")/COUNTA(TRADE_LOG!H$4:H$78),"")
A82: =IF(TRADE_LOG!A79<>"",76,"") | B82: =IF(TRADE_LOG!A79<>"",TRADE_LOG!A79,"") | C82: =IF(TRADE_LOG!H79<>"",TRADE_LOG!H79,"") | D82: =IF(C82<>"",D81+C82,"") | E82: =IFERROR(COUNTIF(TRADE_LOG!H$4:H$79,">0")/COUNTA(TRADE_LOG!H$4:H$79),"")
A83: =IF(TRADE_LOG!A80<>"",77,"") | B83: =IF(TRADE_LOG!A80<>"",TRADE_LOG!A80,"") | C83: =IF(TRADE_LOG!H80<>"",TRADE_LOG!H80,"") | D83: =IF(C83<>"",D82+C83,"") | E83: =IFERROR(COUNTIF(TRADE_LOG!H$4:H$80,">0")/COUNTA(TRADE_LOG!H$4:H$80),"")
A84: =IF(TRADE_LOG!A81<>"",78,"") | B84: =IF(TRADE_LOG!A81<>"",TRADE_LOG!A81,"") | C84: =IF(TRADE_LOG!H81<>"",TRADE_LOG!H81,"") | D84: =IF(C84<>"",D83+C84,"") | E84: =IFERROR(COUNTIF(TRADE_LOG!H$4:H$81,">0")/COUNTA(TRADE_LOG!H$4:H$81),"")
A85: =IF(TRADE_LOG!A82<>"",79,"") | B85: =IF(TRADE_LOG!A82<>"",TRADE_LOG!A82,"") | C85: =IF(TRADE_LOG!H82<>"",TRADE_LOG!H82,"") | D85: =IF(C85<>"",D84+C85,"") | E85: =IFERROR(COUNTIF(TRADE_LOG!H$4:H$82,">0")/COUNTA(TRADE_LOG!H$4:H$82),"")
A86: =IF(TRADE_LOG!A83<>"",80,"") | B86: =IF(TRADE_LOG!A83<>"",TRADE_LOG!A83,"") | C86: =IF(TRADE_LOG!H83<>"",TRADE_LOG!H83,"") | D86: =IF(C86<>"",D85+C86,"") | E86: =IFERROR(COUNTIF(TRADE_LOG!H$4:H$83,">0")/COUNTA(TRADE_LOG!H$4:H$83),"")
A87: =IF(TRADE_LOG!A84<>"",81,"") | B87: =IF(TRADE_LOG!A84<>"",TRADE_LOG!A84,"") | C87: =IF(TRADE_LOG!H84<>"",TRADE_LOG!H84,"") | D87: =IF(C87<>"",D86+C87,"") | E87: =IFERROR(COUNTIF(TRADE_LOG!H$4:H$84,">0")/COUNTA(TRADE_LOG!H$4:H$84),"")
A88: =IF(TRADE_LOG!A85<>"",82,"") | B88: =IF(TRADE_LOG!A85<>"",TRADE_LOG!A85,"") | C88: =IF(TRADE_LOG!H85<>"",TRADE_LOG!H85,"") | D88: =IF(C88<>"",D87+C88,"") | E88: =IFERROR(COUNTIF(TRADE_LOG!H$4:H$85,">0")/COUNTA(TRADE_LOG!H$4:H$85),"")
A89: =IF(TRADE_LOG!A86<>"",83,"") | B89: =IF(TRADE_LOG!A86<>"",TRADE_LOG!A86,"") | C89: =IF(TRADE_LOG!H86<>"",TRADE_LOG!H86,"") | D89: =IF(C89<>"",D88+C89,"") | E89: =IFERROR(COUNTIF(TRADE_LOG!H$4:H$86,">0")/COUNTA(TRADE_LOG!H$4:H$86),"")
A90: =IF(TRADE_LOG!A87<>"",84,"") | B90: =IF(TRADE_LOG!A87<>"",TRADE_LOG!A87,"") | C90: =IF(TRADE_LOG!H87<>"",TRADE_LOG!H87,"") | D90: =IF(C90<>"",D89+C90,"") | E90: =IFERROR(COUNTIF(TRADE_LOG!H$4:H$87,">0")/COUNTA(TRADE_LOG!H$4:H$87),"")
A91: =IF(TRADE_LOG!A88<>"",85,"") | B91: =IF(TRADE_LOG!A88<>"",TRADE_LOG!A88,"") | C91: =IF(TRADE_LOG!H88<>"",TRADE_LOG!H88,"") | D91: =IF(C91<>"",D90+C91,"") | E91: =IFERROR(COUNTIF(TRADE_LOG!H$4:H$88,">0")/COUNTA(TRADE_LOG!H$4:H$88),"")
A92: =IF(TRADE_LOG!A89<>"",86,"") | B92: =IF(TRADE_LOG!A89<>"",TRADE_LOG!A89,"") | C92: =IF(TRADE_LOG!H89<>"",TRADE_LOG!H89,"") | D92: =IF(C92<>"",D91+C92,"") | E92: =IFERROR(COUNTIF(TRADE_LOG!H$4:H$89,">0")/COUNTA(TRADE_LOG!H$4:H$89),"")
A93: =IF(TRADE_LOG!A90<>"",87,"") | B93: =IF(TRADE_LOG!A90<>"",TRADE_LOG!A90,"") | C93: =IF(TRADE_LOG!H90<>"",TRADE_LOG!H90,"") | D93: =IF(C93<>"",D92+C93,"") | E93: =IFERROR(COUNTIF(TRADE_LOG!H$4:H$90,">0")/COUNTA(TRADE_LOG!H$4:H$90),"")
A94: =IF(TRADE_LOG!A91<>"",88,"") | B94: =IF(TRADE_LOG!A91<>"",TRADE_LOG!A91,"") | C94: =IF(TRADE_LOG!H91<>"",TRADE_LOG!H91,"") | D94: =IF(C94<>"",D93+C94,"") | E94: =IFERROR(COUNTIF(TRADE_LOG!H$4:H$91,">0")/COUNTA(TRADE_LOG!H$4:H$91),"")
A95: =IF(TRADE_LOG!A92<>"",89,"") | B95: =IF(TRADE_LOG!A92<>"",TRADE_LOG!A92,"") | C95: =IF(TRADE_LOG!H92<>"",TRADE_LOG!H92,"") | D95: =IF(C95<>"",D94+C95,"") | E95: =IFERROR(COUNTIF(TRADE_LOG!H$4:H$92,">0")/COUNTA(TRADE_LOG!H$4:H$92),"")
A96: =IF(TRADE_LOG!A93<>"",90,"") | B96: =IF(TRADE_LOG!A93<>"",TRADE_LOG!A93,"") | C96: =IF(TRADE_LOG!H93<>"",TRADE_LOG!H93,"") | D96: =IF(C96<>"",D95+C96,"") | E96: =IFERROR(COUNTIF(TRADE_LOG!H$4:H$93,">0")/COUNTA(TRADE_LOG!H$4:H$93),"")
A97: =IF(TRADE_LOG!A94<>"",91,"") | B97: =IF(TRADE_LOG!A94<>"",TRADE_LOG!A94,"") | C97: =IF(TRADE_LOG!H94<>"",TRADE_LOG!H94,"") | D97: =IF(C97<>"",D96+C97,"") | E97: =IFERROR(COUNTIF(TRADE_LOG!H$4:H$94,">0")/COUNTA(TRADE_LOG!H$4:H$94),"")
A98: =IF(TRADE_LOG!A95<>"",92,"") | B98: =IF(TRADE_LOG!A95<>"",TRADE_LOG!A95,"") | C98: =IF(TRADE_LOG!H95<>"",TRADE_LOG!H95,"") | D98: =IF(C98<>"",D97+C98,"") | E98: =IFERROR(COUNTIF(TRADE_LOG!H$4:H$95,">0")/COUNTA(TRADE_LOG!H$4:H$95),"")
A99: =IF(TRADE_LOG!A96<>"",93,"") | B99: =IF(TRADE_LOG!A96<>"",TRADE_LOG!A96,"") | C99: =IF(TRADE_LOG!H96<>"",TRADE_LOG!H96,"") | D99: =IF(C99<>"",D98+C99,"") | E99: =IFERROR(COUNTIF(TRADE_LOG!H$4:H$96,">0")/COUNTA(TRADE_LOG!H$4:H$96),"")
A100: =IF(TRADE_LOG!A97<>"",94,"") | B100: =IF(TRADE_LOG!A97<>"",TRADE_LOG!A97,"") | C100: =IF(TRADE_LOG!H97<>"",TRADE_LOG!H97,"") | D100: =IF(C100<>"",D99+C100,"") | E100: =IFERROR(COUNTIF(TRADE_LOG!H$4:H$97,">0")/COUNTA(TRADE_LOG!H$4:H$97),"")
...

Sheet SETUP_ANALYSIS
A1: ⬡ SETUP PROFITABILITY · BASIC EDITION · AUTO from TRADE_LOG
A2: SETUP | B2: TRADES | C2: WINS | D2: LOSSES | E2: WIN RATE % | F2: AVG PnL | G2: TOTAL PnL | H2: EV SCORE
A3: Breakout | B3: =COUNTIF(TRADE_LOG!D$4:D$2000,A3) | C3: =COUNTIFS(TRADE_LOG!D$4:D$2000,A3,TRADE_LOG!H$4:H$2000,">0") | D3: =COUNTIFS(TRADE_LOG!D$4:D$2000,A3,TRADE_LOG!H$4:H$2000,"<0") | E3: =IFERROR(C3/B3,0) | F3: =IFERROR(AVERAGEIF(TRADE_LOG!D$4:D$2000,A3,TRADE_LOG!H$4:H$2000),0) | G3: =IFERROR(SUMIF(TRADE_LOG!D$4:D$2000,A3,TRADE_LOG!H$4:H$2000),0) | H3: =IFERROR(E3*F3,0)
A4: Breakdown | B4: =COUNTIF(TRADE_LOG!D$4:D$2000,A4) | C4: =COUNTIFS(TRADE_LOG!D$4:D$2000,A4,TRADE_LOG!H$4:H$2000,">0") | D4: =COUNTIFS(TRADE_LOG!D$4:D$2000,A4,TRADE_LOG!H$4:H$2000,"<0") | E4: =IFERROR(C4/B4,0) | F4: =IFERROR(AVERAGEIF(TRADE_LOG!D$4:D$2000,A4,TRADE_LOG!H$4:H$2000),0) | G4: =IFERROR(SUMIF(TRADE_LOG!D$4:D$2000,A4,TRADE_LOG!H$4:H$2000),0) | H4: =IFERROR(E4*F4,0)
A5: Reversal | B5: =COUNTIF(TRADE_LOG!D$4:D$2000,A5) | C5: =COUNTIFS(TRADE_LOG!D$4:D$2000,A5,TRADE_LOG!H$4:H$2000,">0") | D5: =COUNTIFS(TRADE_LOG!D$4:D$2000,A5,TRADE_LOG!H$4:H$2000,"<0") | E5: =IFERROR(C5/B5,0) | F5: =IFERROR(AVERAGEIF(TRADE_LOG!D$4:D$2000,A5,TRADE_LOG!H$4:H$2000),0) | G5: =IFERROR(SUMIF(TRADE_LOG!D$4:D$2000,A5,TRADE_LOG!H$4:H$2000),0) | H5: =IFERROR(E5*F5,0)
A6: Scalping | B6: =COUNTIF(TRADE_LOG!D$4:D$2000,A6) | C6: =COUNTIFS(TRADE_LOG!D$4:D$2000,A6,TRADE_LOG!H$4:H$2000,">0") | D6: =COUNTIFS(TRADE_LOG!D$4:D$2000,A6,TRADE_LOG!H$4:H$2000,"<0") | E6: =IFERROR(C6/B6,0) | F6: =IFERROR(AVERAGEIF(TRADE_LOG!D$4:D$2000,A6,TRADE_LOG!H$4:H$2000),0) | G6: =IFERROR(SUMIF(TRADE_LOG!D$4:D$2000,A6,TRADE_LOG!H$4:H$2000),0) | H6: =IFERROR(E6*F6,0)
A7: Liquidity Grab | B7: =COUNTIF(TRADE_LOG!D$4:D$2000,A7) | C7: =COUNTIFS(TRADE_LOG!D$4:D$2000,A7,TRADE_LOG!H$4:H$2000,">0") | D7: =COUNTIFS(TRADE_LOG!D$4:D$2000,A7,TRADE_LOG!H$4:H$2000,"<0") | E7: =IFERROR(C7/B7,0) | F7: =IFERROR(AVERAGEIF(TRADE_LOG!D$4:D$2000,A7,TRADE_LOG!H$4:H$2000),0) | G7: =IFERROR(SUMIF(TRADE_LOG!D$4:D$2000,A7,TRADE_LOG!H$4:H$2000),0) | H7: =IFERROR(E7*F7,0)
A8: VWAP Reversion | B8: =COUNTIF(TRADE_LOG!D$4:D$2000,A8) | C8: =COUNTIFS(TRADE_LOG!D$4:D$2000,A8,TRADE_LOG!H$4:H$2000,">0") | D8: =COUNTIFS(TRADE_LOG!D$4:D$2000,A8,TRADE_LOG!H$4:H$2000,"<0") | E8: =IFERROR(C8/B8,0) | F8: =IFERROR(AVERAGEIF(TRADE_LOG!D$4:D$2000,A8,TRADE_LOG!H$4:H$2000),0) | G8: =IFERROR(SUMIF(TRADE_LOG!D$4:D$2000,A8,TRADE_LOG!H$4:H$2000),0) | H8: =IFERROR(E8*F8,0)
A9: Opening Range | B9: =COUNTIF(TRADE_LOG!D$4:D$2000,A9) | C9: =COUNTIFS(TRADE_LOG!D$4:D$2000,A9,TRADE_LOG!H$4:H$2000,">0") | D9: =COUNTIFS(TRADE_LOG!D$4:D$2000,A9,TRADE_LOG!H$4:H$2000,"<0") | E9: =IFERROR(C9/B9,0) | F9: =IFERROR(AVERAGEIF(TRADE_LOG!D$4:D$2000,A9,TRADE_LOG!H$4:H$2000),0) | G9: =IFERROR(SUMIF(TRADE_LOG!D$4:D$2000,A9,TRADE_LOG!H$4:H$2000),0) | H9: =IFERROR(E9*F9,0)
A10: Order Block | B10: =COUNTIF(TRADE_LOG!D$4:D$2000,A10) | C10: =COUNTIFS(TRADE_LOG!D$4:D$2000,A10,TRADE_LOG!H$4:H$2000,">0") | D10: =COUNTIFS(TRADE_LOG!D$4:D$2000,A10,TRADE_LOG!H$4:H$2000,"<0") | E10: =IFERROR(C10/B10,0) | F10: =IFERROR(AVERAGEIF(TRADE_LOG!D$4:D$2000,A10,TRADE_LOG!H$4:H$2000),0) | G10: =IFERROR(SUMIF(TRADE_LOG!D$4:D$2000,A10,TRADE_LOG!H$4:H$2000),0) | H10: =IFERROR(E10*F10,0)
A11: Supply/Demand | B11: =COUNTIF(TRADE_LOG!D$4:D$2000,A11) | C11: =COUNTIFS(TRADE_LOG!D$4:D$2000,A11,TRADE_LOG!H$4:H$2000,">0") | D11: =COUNTIFS(TRADE_LOG!D$4:D$2000,A11,TRADE_LOG!H$4:H$2000,"<0") | E11: =IFERROR(C11/B11,0) | F11: =IFERROR(AVERAGEIF(TRADE_LOG!D$4:D$2000,A11,TRADE_LOG!H$4:H$2000),0) | G11: =IFERROR(SUMIF(TRADE_LOG!D$4:D$2000,A11,TRADE_LOG!H$4:H$2000),0) | H11: =IFERROR(E11*F11,0)
A12: Gap Fill | B12: =COUNTIF(TRADE_LOG!D$4:D$2000,A12) | C12: =COUNTIFS(TRADE_LOG!D$4:D$2000,A12,TRADE_LOG!H$4:H$2000,">0") | D12: =COUNTIFS(TRADE_LOG!D$4:D$2000,A12,TRADE_LOG!H$4:H$2000,"<0") | E12: =IFERROR(C12/B12,0) | F12: =IFERROR(AVERAGEIF(TRADE_LOG!D$4:D$2000,A12,TRADE_LOG!H$4:H$2000),0) | G12: =IFERROR(SUMIF(TRADE_LOG!D$4:D$2000,A12,TRADE_LOG!H$4:H$2000),0) | H12: =IFERROR(E12*F12,0)
A13: Other | B13: =COUNTIF(TRADE_LOG!D$4:D$2000,A13) | C13: =COUNTIFS(TRADE_LOG!D$4:D$2000,A13,TRADE_LOG!H$4:H$2000,">0") | D13: =COUNTIFS(TRADE_LOG!D$4:D$2000,A13,TRADE_LOG!H$4:H$2000,"<0") | E13: =IFERROR(C13/B13,0) | F13: =IFERROR(AVERAGEIF(TRADE_LOG!D$4:D$2000,A13,TRADE_LOG!H$4:H$2000),0) | G13: =IFERROR(SUMIF(TRADE_LOG!D$4:D$2000,A13,TRADE_LOG!H$4:H$2000),0) | H13: =IFERROR(E13*F13,0)
A15: © thetradingmindset26 2026 · Basic Edition (₹499) · @thetradingmindset26 · Educational self-improvement tool only. Not investment advice. Unauthorised redistribution prohibited.

Sheet PSYCHOLOGY_LOG
A1: ⬡ PSYCHOLOGY LOG · BASIC EDITION · AUTO from TRADE_LOG | E1: MISTAKE FREQUENCY
A2: EMOTION BEFORE | B2: COUNT | C2: FREQ % | E2: MISTAKE | F2: COUNT | G2: FREQ %
A3: Confident | B3: =COUNTIF(TRADE_LOG!K$4:K$2000,A3) | C3: =IFERROR(B3/COUNTA(TRADE_LOG!K$4:K$2000),0) | E3: Overtrading | F3: — | G3: —
A4: Disciplined | B4: =COUNTIF(TRADE_LOG!K$4:K$2000,A4) | C4: =IFERROR(B4/COUNTA(TRADE_LOG!K$4:K$2000),0) | E4: Early Exit | F4: — | G4: —
A5: Calm | B5: =COUNTIF(TRADE_LOG!K$4:K$2000,A5) | C5: =IFERROR(B5/COUNTA(TRADE_LOG!K$4:K$2000),0) | E5: Late Entry | F5: — | G5: —
A6: Neutral | B6: =COUNTIF(TRADE_LOG!K$4:K$2000,A6) | C6: =IFERROR(B6/COUNTA(TRADE_LOG!K$4:K$2000),0) | E6: Late Exit | F6: — | G6: —
A7: Fearful | B7: =COUNTIF(TRADE_LOG!K$4:K$2000,A7) | C7: =IFERROR(B7/COUNTA(TRADE_LOG!K$4:K$2000),0) | E7: Moved Stop Loss | F7: — | G7: —
A8: Anxious | B8: =COUNTIF(TRADE_LOG!K$4:K$2000,A8) | C8: =IFERROR(B8/COUNTA(TRADE_LOG!K$4:K$2000),0) | E8: Sized Too Large | F8: — | G8: —
A9: Greedy | B9: =COUNTIF(TRADE_LOG!K$4:K$2000,A9) | C9: =IFERROR(B9/COUNTA(TRADE_LOG!K$4:K$2000),0) | E9: Chased Price | F9: — | G9: —
A10: Revenge | B10: =COUNTIF(TRADE_LOG!K$4:K$2000,A10) | C10: =IFERROR(B10/COUNTA(TRADE_LOG!K$4:K$2000),0) | E10: Revenge Trade | F10: — | G10: —
A11: FOMO | B11: =COUNTIF(TRADE_LOG!K$4:K$2000,A11) | C11: =IFERROR(B11/COUNTA(TRADE_LOG!K$4:K$2000),0) | E11: FOMO Entry | F11: — | G11: —
A12: Overconfident | B12: =COUNTIF(TRADE_LOG!K$4:K$2000,A12) | C12: =IFERROR(B12/COUNTA(TRADE_LOG!K$4:K$2000),0) | E12: Broke Rules | F12: — | G12: —
A13: Frustrated | B13: =COUNTIF(TRADE_LOG!K$4:K$2000,A13) | C13: =IFERROR(B13/COUNTA(TRADE_LOG!K$4:K$2000),0)
A14: Satisfied | B14: =COUNTIF(TRADE_LOG!K$4:K$2000,A14) | C14: =IFERROR(B14/COUNTA(TRADE_LOG!K$4:K$2000),0) | E14: ⬆ Upgrade to Pro version to unlock Mistake Tracking
A15: Regretful | B15: =COUNTIF(TRADE_LOG!K$4:K$2000,A15) | C15: =IFERROR(B15/COUNTA(TRADE_LOG!K$4:K$2000),0)
A17: © thetradingmindset26 2026 · Basic Edition (₹499) · @thetradingmindset26 · Educational self-improvement tool only. Not investment advice. Unauthorised redistribution prohibited.

Sheet WEEKLY_REVIEW
A1: ⬡ WEEKLY REVIEW · BASIC EDITION · Type week-end date only — rest is AUTO
A3: WEEK ENDING DATE ← TYPE HERE
A4: Total Trades This Week | B4: =COUNTIFS(TRADE_LOG!A$4:A$2000,">="&DATE(YEAR(B3),MONTH(B3),DAY(B3)-6),TRADE_LOG!A$4:A$2000,"<="&B3)
A5: Weekly PnL | B5: =SUMIFS(TRADE_LOG!H$4:H$2000,TRADE_LOG!A$4:A$2000,">="&DATE(YEAR(B3),MONTH(B3),DAY(B3)-6),TRADE_LOG!A$4:A$2000,"<="&B3)
A6: Win Rate | B6: =IFERROR(COUNTIFS(TRADE_LOG!A$4:A$2000,">="&DATE(YEAR(B3),MONTH(B3),DAY(B3)-6),TRADE_LOG!A$4:A$2000,"<="&B3,TRADE_LOG!H$4:H$2000,">0")/B4,0)
A7: Discipline % | B7: =IFERROR(COUNTIFS(TRADE_LOG!A$4:A$2000,">="&DATE(YEAR(B3),MONTH(B3),DAY(B3)-6),TRADE_LOG!A$4:A$2000,"<="&B3,TRADE_LOG!J$4:J$2000,"Yes")/B4,0)
A9: What went well this week:
A10: 1.
A11: 2.
A12: 3.
A14: What went wrong:
A15: 1.
A16: 2.
A17: 3.
A19: Next week focus setup:
A20: Habit to eliminate:
A21: Daily loss limit (pts):
A23: © thetradingmindset26 2026 · Basic Edition (₹499) · @thetradingmindset26 · Educational self-improvement tool only. Not investment advice. Unauthorised redistribution prohibited.

Sheet AI_PROMPT
A1: ⬡ AI COACHING PROMPT · BASIC EDITION · Copy prompt below → Paste into claude.ai (FREE)
A2: STEPS: 1) Log at least 5 trades 2) Check your live metrics below (rows 5-12) 3) Copy the prompt from rows 15-30 4) Include your metrics 5) Paste into claude.ai (free) or chat.openai.com
A3: UPGRADE TO PRO: Get full automation — AI fills all sections with one click. No copy-paste. thetradingmindset26 Pro at ₹2,999
A4: YOUR LIVE METRICS (auto-calculated from TRADE_LOG):
A5: Total Trades: | B5: =COUNTA(TRADE_LOG!A4:A2000)
A6: Win Rate: | B6: =TEXT(IFERROR(COUNTIF(TRADE_LOG!H4:H2000,">0")/COUNTA(TRADE_LOG!H4:H2000),0),"0.0%")
A7: Total PnL: | B7: =TEXT(IFERROR(SUM(TRADE_LOG!H4:H2000),0),"+#,##0;-#,##0")
A8: Profit Factor: | B8: =TEXT(IFERROR(SUMIF(TRADE_LOG!H4:H2000,">0")/ABS(SUMIF(TRADE_LOG!H4:H2000,"<0")),0),"0.00")
A9: Avg R:R: | B9: =TEXT(IFERROR(AVERAGE(TRADE_LOG!I4:I2000),0),"0.00")
A10: Discipline %: | B10: =TEXT(IFERROR(COUNTIF(TRADE_LOG!J4:J2000,"Yes")/COUNTA(TRADE_LOG!J4:J2000),0),"0.0%")
A11: Top Emotion: | B11: =IFERROR(INDEX(PSYCHOLOGY_LOG!A3:A15,MATCH(MAX(PSYCHOLOGY_LOG!B3:B15),PSYCHOLOGY_LOG!B3:B15,0)),"N/A")
A12: Avg Quality: | B12: =TEXT(IFERROR(AVERAGE(TRADE_LOG!L4:L2000),0),"0.0")&"/10"
A14: PROMPT TO COPY (include your metrics from above):
A15: You are a strict trading coach. Analyze my trading data below and give me coaching. [PASTE YOUR METRICS FROM ROWS 5-12 ABOVE HERE] DELIVER in this exact format: 1. PERFORMANCE REALITY CHECK: (honest, use my numbers) 2. BIGGEST MISTAKE COSTING MONEY: (specific, with evidence) 3. BEST SETUP TO FOCUS ON: (data-backed reason) 4. WORST HABIT TO ELIMINATE: (precise) 5. PSYCHOLOGY PATTERN: (what my top emotion reveals) 6. ACTION PLAN FOR TOMORROW: (3 specific rules) 7. MY GRADE: (A/B/C/D/F + one sentence why) Tone: Strict. Use my numbers. No motivation. No fluff. SEBI NOTE: This is for my personal educational self-review only. Not investment advice.
A34: © thetradingmindset26 2026 · Basic Edition (₹499) · @thetradingmindset26 · Educational self-improvement tool only. Not investment advice. Unauthorised redistribution prohibited.
